linguist
tests
