Metadata-Version: 1.0
Name: linguist
Version: 0.1.1
Summary: Language Savant
Home-page: https://github.com/liluo/linguist
Author: liluo
Author-email: i@liluo.org
License: New BSD
Keywords: linguist,detect,programming,language
Platform: any
